fusesell.py
fusesell-1.3.47.dist-info/licenses/LICENSE
fusesell_local/__init__.py
fusesell_local/api.py
fusesell_local/cli.py
fusesell_local/pipeline.py
fusesell_local/config/__init__.py
fusesell_local/config/default_email_templates.json
fusesell_local/config/default_prompts.json
fusesell_local/config/default_scoring_criteria.json
fusesell_local/config/prompts.py
fusesell_local/config/settings.py
fusesell_local/stages/__init__.py
fusesell_local/stages/base_stage.py
fusesell_local/stages/data_acquisition.py
fusesell_local/stages/data_preparation.py
fusesell_local/stages/follow_up.py
fusesell_local/stages/initial_outreach.py
fusesell_local/stages/lead_scoring.py
fusesell_local/utils/__init__.py
fusesell_local/utils/agent_context.py
fusesell_local/utils/auto_setup.py
fusesell_local/utils/birthday_email_manager.py
fusesell_local/utils/data_manager.py
fusesell_local/utils/event_scheduler.py
fusesell_local/utils/llm_client.py
fusesell_local/utils/logger.py
fusesell_local/utils/output_helpers.py
fusesell_local/utils/timezone_detector.py
fusesell_local/utils/validators.py
fusesell-1.3.47.dist-info/METADATA
fusesell-1.3.47.dist-info/WHEEL
fusesell-1.3.47.dist-info/entry_points.txt
fusesell-1.3.47.dist-info/top_level.txt
fusesell-1.3.47.dist-info/RECORD
