Metadata-Version: 2.4
Name: fusesell
Version: 1.3.47
Summary: Complete AI-powered sales automation pipeline that runs entirely on your local machine.
Author-email: RealTimeX Team <info@realtimex.ai>
License-Expression: MIT
Project-URL: Homepage, https://github.com/rtavytran/fusesell
Project-URL: Source, https://github.com/rtavytran/fusesell
Project-URL: Issues, https://github.com/rtavytran/fusesell/issues
Project-URL: Changelog, https://github.com/rtavytran/fusesell/blob/main/CHANGELOG.md
Requires-Python: >=3.8
License-File: LICENSE
Requires-Dist: openai>=1.0.0
Requires-Dist: requests>=2.25.0
Requires-Dist: beautifulsoup4>=4.9.0
Requires-Dist: python-dateutil>=2.8.0
Requires-Dist: pytz>=2021.1
Provides-Extra: ocr
Requires-Dist: pytesseract>=0.3.8; extra == "ocr"
Requires-Dist: pillow>=8.0.0; extra == "ocr"
Requires-Dist: easyocr>=1.6.0; extra == "ocr"
Provides-Extra: pdf
Requires-Dist: PyPDF2>=3.0.0; extra == "pdf"
Requires-Dist: PyMuPDF>=1.20.0; extra == "pdf"
Provides-Extra: gcv
Requires-Dist: google-cloud-vision>=2.0.0; extra == "gcv"
Provides-Extra: dev
Requires-Dist: psutil>=5.8.0; extra == "dev"
Requires-Dist: pytest>=8.0.0; extra == "dev"
Dynamic: license-file
